LICENSE.rst
MANIFEST.in
README.rst
requirements.txt
setup.py
beddit/__init__.py
beddit/client.py
beddit/compatibility.py
beddit/group.py
beddit/session.py
beddit/sleep.py
beddit/user.py
beddit_python.egg-info/PKG-INFO
beddit_python.egg-info/SOURCES.txt
beddit_python.egg-info/dependency_links.txt
beddit_python.egg-info/requires.txt
beddit_python.egg-info/top_level.txt
beddit_python.egg-info/zip-safe
tests/__init__.py
tests/compatibility.py
tests/test_client.py
tests/test_group.py
tests/test_session.py
tests/test_sleep.py
tests/test_user.py