Metadata-Version: 1.1
Name: beddit-python
Version: 0.1.1
Summary: API client for Beddit sleep tracker
Home-page: https://github.com/giginet/beddit-python
Author: giginet
Author-email: giginet.net@gmail.com
License: MIT
Download-URL: https://github.com/giginet/beddit-python/tarball/master
Keywords: beddit api client sleep IoT
Platform: UNKNOWN
Classifier: Development Status :: 4 - Beta
Classifier: Environment :: Web Environment
Classifier: Intended Audience :: Developers
Classifier: License :: OSI Approved :: MIT License
Classifier: Programming Language :: Python
Classifier: Programming Language :: Python :: 2
Classifier: Programming Language :: Python :: 2.7
Classifier: Programming Language :: Python :: 3
Classifier: Programming Language :: Python :: 3.3
Classifier: Programming Language :: Python :: 3.4
Classifier: Programming Language :: Python :: 3.5
Classifier: Topic :: Internet :: WWW/HTTP
Classifier: Topic :: Software Development :: Libraries
Classifier: Topic :: Software Development :: Libraries :: Python Modules
